{
  "accounts": [
    {
      "name": "Omar Ben Salem",
      "email": "omar.bensalem@example.com",
      "type": "hr",
      "status": "Active",
      "balance": 1500.00
    },
    {
      "name": "Sara Khaldi",
      "email": "sara.khaldi@example.com",
      "type": "employee",
      "status": "Inactive",
      "balance": 0.00
    },
    {
      "name": "Ahmed Mansour",
      "email": "ahmed.mansour@example.com",
      "type": "learner",
      "status": "Active",
      "balance": 320.00
    },
    {
      "name": "Fatma Trabelsi",
      "email": "fatma.trabelsi@example.com",
      "type": "hr",
      "status": "Inactive",
      "balance": 890.50
    },
    {
      "name": "Karim Jaziri",
      "email": "karim.jaziri@example.com",
      "type": "learner",
      "status": "Active",
      "balance": 120.10
    },
    {
      "name": "Mouna Gharbi",
      "email": "mouna.gharbi@example.com",
      "type": "employee",
      "status": "Active",
      "balance": 940.00
    },
    {
      "name": "Slim Dabbabi",
      "email": "slim.dabbabi@example.com",
      "type": "employee",
      "status": "Active",
      "balance": 973.33
    },
    {
      "name": "Rania Saidi",
      "email": "rania.saidi@example.com",
      "type": "learner",
      "status": "Inactive",
      "balance": 45.25
    }
  ]
}
